apportionment/__init__.py
apportionment/methods.py
apportionment-1.0.dist-info/LICENSE
apportionment-1.0.dist-info/METADATA
apportionment-1.0.dist-info/WHEEL
apportionment-1.0.dist-info/top_level.txt
apportionment-1.0.dist-info/RECORD
