Metadata-Version: 2.1
Name: apportionment
Version: 1.0
Summary: A Python implementation of common apportionment methods
Home-page: https://github.com/martinlackner/apportionment/
Author: Martin Lackner
Author-email: unexpected@sent.at
License: MIT License
Project-URL: Bug Tracker, https://github.com/martinlackner/apportionment/issues
Platform: UNKNOWN
Classifier: Programming Language :: Python :: 3
Classifier: Programming Language :: Python :: 3.7
Classifier: Programming Language :: Python :: 3.8
Classifier: Programming Language :: Python :: 3.9
Classifier: Programming Language :: Python :: 3.10
Classifier: License :: OSI Approved :: MIT License
Classifier: Operating System :: OS Independent
Classifier: Intended Audience :: Science/Research
Requires-Python: >=3.7
Requires-Dist: numpy (>=1.20)
Provides-Extra: dev
Requires-Dist: pytest (>=6) ; extra == 'dev'
Requires-Dist: coverage[toml] (>=5.3) ; extra == 'dev'
Requires-Dist: black (==22.1.0) ; extra == 'dev'
